[{"Lst": -15, "phi": 41.382, "Lloc": -2.175, "clim": 2, "type_roof_n1": "roof_flat","type_roof_n2": "roof_flat","type_roof_n3": "roof_tilt", "gamma_n1": 0, "gamma_n2": 0, "gamma_n3": 0,  "beta_n1": 10, "beta_n2": 10, "beta_n3": 20, "pva_n1":92.09, "pva_n2": 0, "pva_n3": 0,  "theta_n1": [0, 0, 0, 0, 0, 0, 0, 0, 0, 0, 0, 0, 0, 0, 0, 0], "theta_n2": [0, 0, 0, 0, 0, 0, 0, 0, 0, 0, 0, 0, 0, 0, 0, 0], "theta_n3": [0, 0, 0, 0, 0, 0, 0, 0, 0, 0, 0, 0, 0, 0, 0, 0], "numV": 10},{"Lst": -15, "phi": 41.382, "Lloc": -2.175, "clim": 2, "type_roof_n1": "roof_flat","type_roof_n2": "roof_flat","type_roof_n3": "roof_tilt", "gamma_n1": 0, "gamma_n2": 0, "gamma_n3": 0,  "beta_n1": 10, "beta_n2": 10, "beta_n3": 20, "pva_n1":92.09, "pva_n2": 0, "pva_n3": 0,  "theta_n1": [0, 0, 0, 0, 0, 0, 0, 0, 0, 0, 0, 0, 0, 0, 0, 0], "theta_n2": [0, 0, 0, 0, 0, 0, 0, 0, 0, 0, 0, 0, 0, 0, 0, 0], "theta_n3": [0, 0, 0, 0, 0, 0, 0, 0, 0, 0, 0, 0, 0, 0, 0, 0], "numV": 1}]